src/__init__.py
src/pazok.py
pazok.lib1-3.dist-info/LICENSE.txt
pazok.lib1-3.dist-info/METADATA
pazok.lib1-3.dist-info/WHEEL
pazok.lib1-3.dist-info/top_level.txt
pazok.lib1-3.dist-info/RECORD
