Metadata-Version: 2.1
Name: pazok.lib1
Version: 3
Author: b_azo
License-File: LICENSE.txt
